[
 {
  "id": 1,
  "firstname": "Ignacio",
  "lastname": "Zavalla",
  "email": "izava@devsign.com",
  "password": "isaBest149",
  "category": "admin",
  "image": "/images/users/admin_01.png"
 },
 {
  "id": 2,
  "firstname": "Deymer",
  "lastname": "Espinosa",
  "email": "dey_es@devsign.com",
  "password": "isaBest149",
  "category": "admin",
  "image": "/images/users/admin_01.png"
 },
 {
  "id": 3,
  "firstname": "Juan",
  "lastname": "Lasota",
  "email": "juanfutbol94@devsign.com",
  "password": "isaBest149",
  "category": "admin",
  "image": "/images/users/admin_01.png"
 },
 {
  "id": 4,
  "firstname": "Isabel",
  "lastname": "Rojas",
  "email": "isarojas@devsign.com",
  "password": "isaBest149",
  "category": "admin",
  "image": "/images/users/admin_01.png"
 },
 {
  "id": 5,
  "firstname": "Francisco",
  "lastname": "Casagrande",
  "email": "francasas@devsign.com",
  "password": "isaBest149",
  "category": "user",
  "image": "/images/users/user_01.png"
 },
 {
  "id": 6,
  "firstname": "Jose",
  "lastname": "Figueroa",
  "email": "jose_f@devsign.com",
  "password": "isaBest149",
  "category": "user",
  "image": "/images/users/user_01.png"
 },
 {
  "id": 7,
  "firstname": "mariana",
  "lastname": "Romero",
  "email": "mariromero@devsign.com",
  "password": "isaBest149",
  "category": "user",
  "image": "/images/users/user_01.png"
 },
 {
  "id": 8,
  "firstname": "Celia",
  "lastname": "Ahumada",
  "email": "celia_03@devsign.com",
  "password": "isaBest149",
  "category": "user",
  "image": "/images/users/user_01.png"
 },
 {
  "id": 9,
  "firstname": "Federico",
  "lastname": "Delfino",
  "email": "fede_delf@devsign.com",
  "password": "isaBest149",
  "category": "user",
  "image": "/images/users/user_01.png"
 },
 {
  "id": 10,
  "firstname": "Lucia",
  "lastname": "Inostrosa",
  "email": "lu_inos@devsign.com",
  "password": "isaBest149",
  "category": "user",
  "image": "/images/users/user_01.png"
 },
 {
  "id": 11,
  "nombre": "Ignacio",
  "logUser": "Zavalla",
  "email": "ignaciomzavalla@gmail.com",
  "password": "asdasd",
  "repeat_password": "asdasd"
 },
 {
  "id": 12,
  "nombre": "Ricardo",
  "logUser": "Fulbito",
  "email": "ricardito@algo.com",
  "password": "asdasd",
  "repeat_password": "asdasd"
 },
 {
  "id": 13,
  "nombre": "Romeo Santos",
  "logUser": "Romeito",
  "email": "rome@algo.com",
  "password": "asdasd",
  "repeat_password": "asdasd",
  "image": "image-1651943470446-932216442.png"
 },
 {
  "id": 14,
  "nombre": "Prueba Imagen Default",
  "logUser": "andará???",
  "email": "imagen_default@si.com",
  "password": "asdasd",
  "repeat_password": "asdasd",
  "image": "user_01.png"
 },
 {
  "id": 15,
  "nombre": "asdasd",
  "logUser": "asd",
  "email": "ignaciomzavalla@gmail.com",
  "password": "asdasd",
  "repeat_password": "asdasd",
  "image": "user_01.png"
 },
 {
  "id": 16,
  "nombre": "asdasd",
  "logUser": "asdasd",
  "email": "ignaciomzavalla@gmail.com",
  "password": "asdasd",
  "repeat_password": "asdasd",
  "image": "user_01.png"
 }
]